{"nodes": [{"color": "rgb(153,255,0)", "label": "0", "y": 997.3, "x": 1142.4, "id": "0", "size": 1.0}, {"color": "rgb(153,255,0)", "label": "1", "y": 767.1, "x": 1181.7, "id": "1", "size": 1.0}, {"color": "rgb(153,255,0)", "label": "2", "y": 762.47, "x": 726.0, "id": "2", "size": 1.0}, {"color": "rgb(153,255,0)", "label": "3", "y": 1761.5, "x": 1441.7, "id": "3", "size": 1.0}, {"color": "rgb(153,255,0)", "label": "4", "y": 803.08, "x": 758.67, "id": "4", "size": 1.0}, {"color": "rgb(153,255,0)", "label": "5", "y": 1396.6, "x": 1247.4, "id": "5", "size": 1.0}, {"color": "rgb(153,255,0)", "label": "6", "y": 1092.8, "x": 359.14, "id": "6", "size": 1.0}, {"color": "rgb(153,255,0)", "label": "7", "y": 672.84, "x": 989.27, "id": "7", "size": 1.0}, {"color": "rgb(153,255,0)", "label": "8", "y": 1045.7, "x": 990.63, "id": "8", "size": 1.0}, {"color": "rgb(153,255,0)", "label": "9", "y": 803.97, "x": 1362.9, "id": "9", "size": 1.0}, {"color": "rgb(153,255,0)", "label": "10", "y": 974.77, "x": 701.41, "id": "10", "size": 1.0}, {"color": "rgb(153,255,0)", "label": "11", "y": 883.12, "x": 523.46, "id": "11", "size": 1.0}, {"color": "rgb(153,255,0)", "label": "12", "y": 1019.9, "x": 1201.4, "id": "12", "size": 1.0}, {"color": "rgb(153,255,0)", "label": "13", "y": 1624.0, "x": 655.93, "id": "13", "size": 1.0}, {"color": "rgb(153,255,0)", "label": "14", "y": 1452.4, "x": 1294.6, "id": "14", "size": 1.0}, {"color": "rgb(153,255,0)", "label": "15", "y": 817.83, "x": 1003.4, "id": "15", "size": 1.0}, {"color": "rgb(153,255,0)", "label": "16", "y": 1086.3, "x": 406.14, "id": "16", "size": 1.0}, {"color": "rgb(153,255,0)", "label": "17", "y": 1080.2, "x": 1603.2, "id": "17", "size": 1.0}, {"color": "rgb(153,255,0)", "label": "18", "y": 1421.7, "x": 1191.4, "id": "18", "size": 1.0}, {"color": "rgb(153,255,0)", "label": "19", "y": 1078.0, "x": 1563.7, "id": "19", "size": 1.0}, {"color": "rgb(153,255,0)", "label": "20", "y": 1364.1, "x": 694.81, "id": "20", "size": 1.0}, {"color": "rgb(153,255,0)", "label": "21", "y": 1041.3, "x": 1857.3, "id": "21", "size": 1.0}, {"color": "rgb(153,255,0)", "label": "22", "y": 1637.9, "x": 1045.0, "id": "22", "size": 1.0}, {"color": "rgb(153,255,0)", "label": "23", "y": 1229.4, "x": 1534.7, "id": "23", "size": 1.0}, {"color": "rgb(153,255,0)", "label": "24", "y": 1261.3, "x": 1523.5, "id": "24", "size": 1.0}, {"color": "rgb(153,255,0)", "label": "25", "y": 1362.7, "x": 1736.3, "id": "25", "size": 1.0}, {"color": "rgb(153,255,0)", "label": "26", "y": 1645.5, "x": 1130.6, "id": "26", "size": 1.0}, {"color": "rgb(153,255,0)", "label": "27", "y": 1609.0, "x": 1328.7, "id": "27", "size": 1.0}, {"color": "rgb(153,255,0)", "label": "28", "y": 846.18, "x": 1240.7, "id": "28", "size": 1.0}, {"color": "rgb(153,255,0)", "label": "29", "y": 1125.6, "x": 1120.8, "id": "29", "size": 1.0}, {"color": "rgb(153,255,0)", "label": "30", "y": 1487.0, "x": 1683.5, "id": "30", "size": 1.0}, {"color": "rgb(153,255,0)", "label": "31", "y": 1185.8, "x": 1948.1, "id": "31", "size": 1.0}, {"color": "rgb(153,255,0)", "label": "32", "y": 1156.8, "x": 579.64, "id": "32", "size": 1.0}, {"color": "rgb(153,255,0)", "label": "33", "y": 1578.6, "x": 1085.5, "id": "33", "size": 1.0}, {"color": "rgb(153,255,0)", "label": "34", "y": 1559.6, "x": 947.87, "id": "34", "size": 1.0}, {"color": "rgb(153,255,0)", "label": "35", "y": 883.93, "x": 1287.7, "id": "35", "size": 1.0}, {"color": "rgb(153,255,0)", "label": "36", "y": 1458.4, "x": 1105.8, "id": "36", "size": 1.0}, {"color": "rgb(153,255,0)", "label": "37", "y": 1152.7, "x": 1440.3, "id": "37", "size": 1.0}, {"color": "rgb(153,255,0)", "label": "38", "y": 1358.3, "x": 1206.6, "id": "38", "size": 1.0}, {"color": "rgb(153,255,0)", "label": "39", "y": 1153.8, "x": 660.69, "id": "39", "size": 1.0}, {"color": "rgb(153,255,0)", "label": "40", "y": 1800.2, "x": 653.04, "id": "40", "size": 1.0}, {"color": "rgb(153,255,0)", "label": "41", "y": 1567.1, "x": 1173.6, "id": "41", "size": 1.0}, {"color": "rgb(153,255,0)", "label": "42", "y": 878.35, "x": 1850.9, "id": "42", "size": 1.0}, {"color": "rgb(153,255,0)", "label": "43", "y": 1355.9, "x": 1331.2, "id": "43", "size": 1.0}, {"color": "rgb(153,255,0)", "label": "44", "y": 836.01, "x": 938.36, "id": "44", "size": 1.0}, {"color": "rgb(153,255,0)", "label": "45", "y": 663.07, "x": 1236.7, "id": "45", "size": 1.0}, {"color": "rgb(153,255,0)", "label": "46", "y": 1043.4, "x": 1476.5, "id": "46", "size": 1.0}, {"color": "rgb(153,255,0)", "label": "47", "y": 755.15, "x": 877.32, "id": "47", "size": 1.0}, {"color": "rgb(153,255,0)", "label": "48", "y": 789.29, "x": 1181.0, "id": "48", "size": 1.0}, {"color": "rgb(153,255,0)", "label": "49", "y": 957.82, "x": 1554.5, "id": "49", "size": 1.0}, {"color": "rgb(153,255,0)", "label": "50", "y": 1504.4, "x": 1232.2, "id": "50", "size": 1.0}, {"color": "rgb(153,255,0)", "label": "51", "y": 1287.9, "x": 1262.6, "id": "51", "size": 1.0}, {"color": "rgb(153,255,0)", "label": "52", "y": 1499.9, "x": 954.81, "id": "52", "size": 1.0}, {"color": "rgb(153,255,0)", "label": "53", "y": 926.9, "x": 1546.3, "id": "53", "size": 1.0}, {"color": "rgb(153,255,0)", "label": "54", "y": 1517.9, "x": 1079.4, "id": "54", "size": 1.0}, {"color": "rgb(153,255,0)", "label": "55", "y": 686.78, "x": 1387.8, "id": "55", "size": 1.0}, {"color": "rgb(153,255,0)", "label": "56", "y": 1084.5, "x": 1249.3, "id": "56", "size": 1.0}, {"color": "rgb(153,255,0)", "label": "57", "y": 1333.4, "x": 491.12, "id": "57", "size": 1.0}, {"color": "rgb(153,255,0)", "label": "58", "y": 1994.2, "x": 389.34, "id": "58", "size": 1.0}, {"color": "rgb(153,255,0)", "label": "59", "y": 1591.3, "x": 781.57, "id": "59", "size": 1.0}, {"color": "rgb(153,255,0)", "label": "60", "y": 1790.7, "x": 1147.2, "id": "60", "size": 1.0}, {"color": "rgb(153,255,0)", "label": "61", "y": 1419.6, "x": 1645.6, "id": "61", "size": 1.0}, {"color": "rgb(153,255,0)", "label": "62", "y": 592.46, "x": 1248.2, "id": "62", "size": 1.0}, {"color": "rgb(153,255,0)", "label": "64", "y": 1098.6, "x": 1321.0, "id": "64", "size": 1.0}, {"color": "rgb(153,255,0)", "label": "65", "y": 599.41, "x": 950.9, "id": "65", "size": 1.0}, {"color": "rgb(153,255,0)", "label": "66", "y": 1705.8, "x": 1597.6, "id": "66", "size": 1.0}, {"color": "rgb(153,255,0)", "label": "67", "y": 1464.7, "x": 772.01, "id": "67", "size": 1.0}, {"color": "rgb(153,255,0)", "label": "68", "y": 694.04, "x": 1042.8, "id": "68", "size": 1.0}, {"color": "rgb(153,255,0)", "label": "69", "y": 1487.2, "x": 1237.0, "id": "69", "size": 1.0}, {"color": "rgb(153,255,0)", "label": "70", "y": 882.43, "x": 678.42, "id": "70", "size": 1.0}, {"color": "rgb(153,255,0)", "label": "72", "y": 1170.8, "x": 1636.3, "id": "72", "size": 1.0}, {"color": "rgb(153,255,0)", "label": "73", "y": 988.18, "x": 1283.6, "id": "73", "size": 1.0}, {"color": "rgb(153,255,0)", "label": "74", "y": 1252.0, "x": 1074.0, "id": "74", "size": 1.0}, {"color": "rgb(153,255,0)", "label": "76", "y": 1278.2, "x": 902.58, "id": "76", "size": 1.0}, {"color": "rgb(153,255,0)", "label": "77", "y": 1045.9, "x": 1723.4, "id": "77", "size": 1.0}, {"color": "rgb(153,255,0)", "label": "78", "y": 951.55, "x": 1346.8, "id": "78", "size": 1.0}, {"color": "rgb(153,255,0)", "label": "79", "y": 939.55, "x": 1411.6, "id": "79", "size": 1.0}, {"color": "rgb(153,255,0)", "label": "80", "y": 1422.4, "x": 843.24, "id": "80", "size": 1.0}, {"color": "rgb(153,255,0)", "label": "82", "y": 1124.6, "x": 1149.0, "id": "82", "size": 1.0}, {"color": "rgb(153,255,0)", "label": "83", "y": 1374.6, "x": 1408.5, "id": "83", "size": 1.0}, {"color": "rgb(153,255,0)", "label": "84", "y": 1151.3, "x": 437.04, "id": "84", "size": 1.0}, {"color": "rgb(153,255,0)", "label": "86", "y": 1537.7, "x": 333.01, "id": "86", "size": 1.0}, {"color": "rgb(153,255,0)", "label": "87", "y": 1004.0, "x": 1648.4, "id": "87", "size": 1.0}, {"color": "rgb(153,255,0)", "label": "88", "y": 1434.6, "x": 1375.2, "id": "88", "size": 1.0}, {"color": "rgb(153,255,0)", "label": "89", "y": 1110.4, "x": 558.47, "id": "89", "size": 1.0}, {"color": "rgb(153,255,0)", "label": "91", "y": 834.8, "x": 379.68, "id": "91", "size": 1.0}, {"color": "rgb(153,255,0)", "label": "92", "y": 1363.7, "x": 856.91, "id": "92", "size": 1.0}, {"color": "rgb(153,255,0)", "label": "93", "y": 1426.7, "x": 1071.6, "id": "93", "size": 1.0}, {"color": "rgb(153,255,0)", "label": "94", "y": 463.45, "x": 1564.8, "id": "94", "size": 1.0}, {"color": "rgb(153,255,0)", "label": "95", "y": 1120.8, "x": 1585.6, "id": "95", "size": 1.0}, {"color": "rgb(153,255,0)", "label": "96", "y": 936.95, "x": 1062.4, "id": "96", "size": 1.0}, {"color": "rgb(153,255,0)", "label": "97", "y": 1163.9, "x": 1590.2, "id": "97", "size": 1.0}, {"color": "rgb(153,255,0)", "label": "98", "y": 936.37, "x": 1297.7, "id": "98", "size": 1.0}, {"color": "rgb(153,255,0)", "label": "99", "y": 1160.8, "x": 1123.0, "id": "99", "size": 1.0}, {"color": "rgb(153,255,0)", "label": "100", "y": 1534.1, "x": 616.32, "id": "100", "size": 1.0}, {"color": "rgb(153,255,0)", "label": "102", "y": 1008.9, "x": 888.8, "id": "102", "size": 1.0}, {"color": "rgb(153,255,0)", "label": "103", "y": 723.38, "x": 865.93, "id": "103", "size": 1.0}, {"color": "rgb(153,255,0)", "label": "104", "y": 1349.0, "x": 959.84, "id": "104", "size": 1.0}, {"color": "rgb(153,255,0)", "label": "105", "y": 1648.9, "x": 1239.9, "id": "105", "size": 1.0}, {"color": "rgb(153,255,0)", "label": "106", "y": 869.56, "x": 972.83, "id": "106", "size": 1.0}, {"color": "rgb(153,255,0)", "label": "107", "y": 1192.3, "x": 1127.8, "id": "107", "size": 1.0}, {"color": "rgb(153,255,0)", "label": "108", "y": 1721.4, "x": 676.88, "id": "108", "size": 1.0}, {"color": "rgb(153,255,0)", "label": "109", "y": 1861.9, "x": 1321.3, "id": "109", "size": 1.0}, {"color": "rgb(153,255,0)", "label": "111", "y": 1810.4, "x": 727.49, "id": "111", "size": 1.0}, {"color": "rgb(153,255,0)", "label": "112", "y": 944.89, "x": 1573.8, "id": "112", "size": 1.0}, {"color": "rgb(153,255,0)", "label": "113", "y": 722.04, "x": 741.2, "id": "113", "size": 1.0}, {"color": "rgb(153,255,0)", "label": "114", "y": 1462.9, "x": 1215.9, "id": "114", "size": 1.0}, {"color": "rgb(153,255,0)", "label": "115", "y": 1555.0, "x": 1327.7, "id": "115", "size": 1.0}, {"color": "rgb(153,255,0)", "label": "116", "y": 1128.9, "x": 1393.6, "id": "116", "size": 1.0}, {"color": "rgb(153,255,0)", "label": "117", "y": 781.29, "x": 1480.9, "id": "117", "size": 1.0}, {"color": "rgb(153,255,0)", "label": "118", "y": 632.89, "x": 1155.4, "id": "118", "size": 1.0}, {"color": "rgb(153,255,0)", "label": "119", "y": 1380.3, "x": 1904.9, "id": "119", "size": 1.0}, {"color": "rgb(153,255,0)", "label": "120", "y": 617.03, "x": 1085.6, "id": "120", "size": 1.0}, {"color": "rgb(153,255,0)", "label": "121", "y": 1112.5, "x": 760.73, "id": "121", "size": 1.0}, {"color": "rgb(153,255,0)", "label": "122", "y": 787.76, "x": 1307.0, "id": "122", "size": 1.0}, {"color": "rgb(153,255,0)", "label": "123", "y": 697.5, "x": 1385.4, "id": "123", "size": 1.0}, {"color": "rgb(153,255,0)", "label": "124", "y": 1130.9, "x": 599.77, "id": "124", "size": 1.0}, {"color": "rgb(153,255,0)", "label": "125", "y": 1090.2, "x": 955.42, "id": "125", "size": 1.0}, {"color": "rgb(153,255,0)", "label": "126", "y": 1567.2, "x": 1265.2, "id": "126", "size": 1.0}, {"color": "rgb(153,255,0)", "label": "127", "y": 851.9, "x": 577.21, "id": "127", "size": 1.0}, {"color": "rgb(153,255,0)", "label": "128", "y": 1667.1, "x": 1002.0, "id": "128", "size": 1.0}, {"color": "rgb(153,255,0)", "label": "129", "y": 1091.0, "x": 786.38, "id": "129", "size": 1.0}, {"color": "rgb(153,255,0)", "label": "130", "y": 1542.6, "x": 1578.7, "id": "130", "size": 1.0}, {"color": "rgb(153,255,0)", "label": "131", "y": 1302.0, "x": 531.74, "id": "131", "size": 1.0}, {"color": "rgb(153,255,0)", "label": "132", "y": 941.72, "x": 669.45, "id": "132", "size": 1.0}, {"color": "rgb(153,255,0)", "label": "133", "y": 1230.8, "x": 1910.7, "id": "133", "size": 1.0}, {"color": "rgb(153,255,0)", "label": "134", "y": 1363.3, "x": 1619.7, "id": "134", "size": 1.0}, {"color": "rgb(153,255,0)", "label": "135", "y": 739.26, "x": 1046.3, "id": "135", "size": 1.0}, {"color": "rgb(153,255,0)", "label": "136", "y": 957.24, "x": 854.03, "id": "136", "size": 1.0}, {"color": "rgb(153,255,0)", "label": "137", "y": 809.46, "x": 1127.1, "id": "137", "size": 1.0}, {"color": "rgb(153,255,0)", "label": "138", "y": 1503.2, "x": 1766.7, "id": "138", "size": 1.0}, {"color": "rgb(153,255,0)", "label": "139", "y": 1222.1, "x": 981.92, "id": "139", "size": 1.0}, {"color": "rgb(153,255,0)", "label": "140", "y": 1381.7, "x": 835.48, "id": "140", "size": 1.0}, {"color": "rgb(153,255,0)", "label": "141", "y": 1176.4, "x": 1392.7, "id": "141", "size": 1.0}, {"color": "rgb(153,255,0)", "label": "142", "y": 1540.3, "x": 828.29, "id": "142", "size": 1.0}, {"color": "rgb(153,255,0)", "label": "143", "y": 877.04, "x": 815.61, "id": "143", "size": 1.0}, {"color": "rgb(153,255,0)", "label": "144", "y": 905.76, "x": 1150.1, "id": "144", "size": 1.0}, {"color": "rgb(153,255,0)", "label": "145", "y": 1154.7, "x": 1225.0, "id": "145", "size": 1.0}, {"color": "rgb(153,255,0)", "label": "146", "y": 1626.1, "x": 766.52, "id": "146", "size": 1.0}, {"color": "rgb(153,255,0)", "label": "147", "y": 787.67, "x": 1770.9, "id": "147", "size": 1.0}, {"color": "rgb(153,255,0)", "label": "148", "y": 1286.2, "x": 1333.6, "id": "148", "size": 1.0}, {"color": "rgb(153,255,0)", "label": "149", "y": 1524.0, "x": 1470.1, "id": "149", "size": 1.0}, {"color": "rgb(153,255,0)", "label": "150", "y": 1221.5, "x": 959.29, "id": "150", "size": 1.0}, {"color": "rgb(153,255,0)", "label": "152", "y": 908.7, "x": 936.47, "id": "152", "size": 1.0}, {"color": "rgb(153,255,0)", "label": "153", "y": 974.33, "x": 852.44, "id": "153", "size": 1.0}, {"color": "rgb(153,255,0)", "label": "154", "y": 883.28, "x": 699.68, "id": "154", "size": 1.0}, {"color": "rgb(153,255,0)", "label": "155", "y": 1287.2, "x": 588.84, "id": "155", "size": 1.0}, {"color": "rgb(153,255,0)", "label": "156", "y": 1608.8, "x": 643.13, "id": "156", "size": 1.0}, {"color": "rgb(153,255,0)", "label": "157", "y": 1312.8, "x": 1410.7, "id": "157", "size": 1.0}, {"color": "rgb(153,255,0)", "label": "158", "y": 1118.2, "x": 1838.0, "id": "158", "size": 1.0}, {"color": "rgb(153,255,0)", "label": "159", "y": 1396.9, "x": 1016.5, "id": "159", "size": 1.0}, {"color": "rgb(153,255,0)", "label": "160", "y": 695.22, "x": 1735.9, "id": "160", "size": 1.0}, {"color": "rgb(153,255,0)", "label": "161", "y": 1655.0, "x": 1206.1, "id": "161", "size": 1.0}, {"color": "rgb(153,255,0)", "label": "162", "y": 1236.7, "x": 1117.9, "id": "162", "size": 1.0}, {"color": "rgb(153,255,0)", "label": "163", "y": 2028.8, "x": 734.88, "id": "163", "size": 1.0}, {"color": "rgb(153,255,0)", "label": "164", "y": 1430.4, "x": 520.95, "id": "164", "size": 1.0}, {"color": "rgb(153,255,0)", "label": "165", "y": 1535.7, "x": 851.05, "id": "165", "size": 1.0}, {"color": "rgb(153,255,0)", "label": "166", "y": 995.69, "x": 672.21, "id": "166", "size": 1.0}, {"color": "rgb(153,255,0)", "label": "167", "y": 1217.0, "x": 995.67, "id": "167", "size": 1.0}, {"color": "rgb(153,255,0)", "label": "168", "y": 1174.4, "x": 1902.9, "id": "168", "size": 1.0}, {"color": "rgb(153,255,0)", "label": "169", "y": 1128.0, "x": 1234.5, "id": "169", "size": 1.0}, {"color": "rgb(153,255,0)", "label": "170", "y": 792.7, "x": 881.73, "id": "170", "size": 1.0}, {"color": "rgb(153,255,0)", "label": "171", "y": 1183.9, "x": 832.8, "id": "171", "size": 1.0}, {"color": "rgb(153,255,0)", "label": "172", "y": 1596.9, "x": 1767.5, "id": "172", "size": 1.0}, {"color": "rgb(153,255,0)", "label": "173", "y": 816.43, "x": 1454.7, "id": "173", "size": 1.0}, {"color": "rgb(153,255,0)", "label": "174", "y": 1046.0, "x": 466.5, "id": "174", "size": 1.0}, {"color": "rgb(153,255,0)", "label": "175", "y": 1148.0, "x": 687.39, "id": "175", "size": 1.0}, {"color": "rgb(153,255,0)", "label": "176", "y": 859.1, "x": 1044.7, "id": "176", "size": 1.0}, {"color": "rgb(153,255,0)", "label": "177", "y": 1510.2, "x": 1111.6, "id": "177", "size": 1.0}, {"color": "rgb(153,255,0)", "label": "178", "y": 1456.2, "x": 1567.2, "id": "178", "size": 1.0}, {"color": "rgb(153,255,0)", "label": "179", "y": 1649.3, "x": 1487.7, "id": "179", "size": 1.0}, {"color": "rgb(153,255,0)", "label": "180", "y": 1043.9, "x": 1942.8, "id": "180", "size": 1.0}, {"color": "rgb(153,255,0)", "label": "181", "y": 1932.4, "x": 942.5, "id": "181", "size": 1.0}, {"color": "rgb(153,255,0)", "label": "182", "y": 816.76, "x": 970.88, "id": "182", "size": 1.0}, {"color": "rgb(153,255,0)", "label": "183", "y": 1656.5, "x": 543.24, "id": "183", "size": 1.0}, {"color": "rgb(153,255,0)", "label": "184", "y": 1847.1, "x": 1002.8, "id": "184", "size": 1.0}, {"color": "rgb(153,255,0)", "label": "185", "y": 924.4, "x": 999.51, "id": "185", "size": 1.0}, {"color": "rgb(153,255,0)", "label": "186", "y": 1011.3, "x": 642.08, "id": "186", "size": 1.0}, {"color": "rgb(153,255,0)", "label": "187", "y": 1379.5, "x": 489.35, "id": "187", "size": 1.0}, {"color": "rgb(153,255,0)", "label": "188", "y": 884.39, "x": 657.07, "id": "188", "size": 1.0}, {"color": "rgb(153,255,0)", "label": "189", "y": 990.64, "x": 587.74, "id": "189", "size": 1.0}, {"color": "rgb(153,255,0)", "label": "190", "y": 930.93, "x": 576.62, "id": "190", "size": 1.0}, {"color": "rgb(153,255,0)", "label": "191", "y": 756.65, "x": 1109.0, "id": "191", "size": 1.0}, {"color": "rgb(153,255,0)", "label": "192", "y": 2010.8, "x": 2329.3, "id": "192", "size": 1.0}, {"color": "rgb(153,255,0)", "label": "193", "y": 719.26, "x": 849.87, "id": "193", "size": 1.0}, {"color": "rgb(153,255,0)", "label": "194", "y": 1084.3, "x": 1182.4, "id": "194", "size": 1.0}, {"color": "rgb(153,255,0)", "label": "195", "y": 531.54, "x": 1176.2, "id": "195", "size": 1.0}, {"color": "rgb(153,255,0)", "label": "196", "y": 1240.2, "x": 1252.5, "id": "196", "size": 1.0}, {"color": "rgb(153,255,0)", "label": "197", "y": 1165.4, "x": 775.72, "id": "197", "size": 1.0}, {"color": "rgb(153,255,0)", "label": "199", "y": 1232.1, "x": 436.67, "id": "199", "size": 1.0}, {"color": "rgb(153,255,0)", "label": "200", "y": 1503.7, "x": 434.89, "id": "200", "size": 1.0}, {"color": "rgb(153,255,0)", "label": "201", "y": 1827.0, "x": 1338.6, "id": "201", "size": 1.0}, {"color": "rgb(153,255,0)", "label": "202", "y": 1480.2, "x": 878.29, "id": "202", "size": 1.0}, {"color": "rgb(153,255,0)", "label": "203", "y": 1289.2, "x": 851.77, "id": "203", "size": 1.0}, {"color": "rgb(153,255,0)", "label": "204", "y": 1451.2, "x": 554.73, "id": "204", "size": 1.0}, {"color": "rgb(153,255,0)", "label": "205", "y": 1222.3, "x": 482.58, "id": "205", "size": 1.0}, {"color": "rgb(153,255,0)", "label": "206", "y": 1387.7, "x": 917.46, "id": "206", "size": 1.0}, {"color": "rgb(153,255,0)", "label": "207", "y": 1490.2, "x": 480.68, "id": "207", "size": 1.0}, {"color": "rgb(153,255,0)", "label": "208", "y": 1356.4, "x": 612.78, "id": "208", "size": 1.0}, {"color": "rgb(153,255,0)", "label": "209", "y": 1622.6, "x": 732.64, "id": "209", "size": 1.0}, {"color": "rgb(153,255,0)", "label": "210", "y": 1368.0, "x": 1326.5, "id": "210", "size": 1.0}, {"color": "rgb(153,255,0)", "label": "211", "y": 1652.6, "x": 1310.1, "id": "211", "size": 1.0}, {"color": "rgb(153,255,0)", "label": "213", "y": 922.47, "x": 1276.3, "id": "213", "size": 1.0}, {"color": "rgb(153,255,0)", "label": "214", "y": 987.34, "x": 878.54, "id": "214", "size": 1.0}, {"color": "rgb(153,255,0)", "label": "215", "y": 1135.3, "x": 1336.0, "id": "215", "size": 1.0}, {"color": "rgb(153,255,0)", "label": "216", "y": 940.54, "x": 1943.4, "id": "216", "size": 1.0}, {"color": "rgb(153,255,0)", "label": "217", "y": 1092.4, "x": 848.76, "id": "217", "size": 1.0}, {"color": "rgb(153,255,0)", "label": "218", "y": 1303.4, "x": 1234.0, "id": "218", "size": 1.0}, {"color": "rgb(153,255,0)", "label": "219", "y": 1241.6, "x": 650.85, "id": "219", "size": 1.0}, {"color": "rgb(153,255,0)", "label": "220", "y": 899.58, "x": 1846.3, "id": "220", "size": 1.0}, {"color": "rgb(153,255,0)", "label": "221", "y": 1935.7, "x": 982.92, "id": "221", "size": 1.0}, {"color": "rgb(153,255,0)", "label": "222", "y": 1537.0, "x": 573.5, "id": "222", "size": 1.0}, {"color": "rgb(153,255,0)", "label": "223", "y": 970.38, "x": 750.5, "id": "223", "size": 1.0}, {"color": "rgb(153,255,0)", "label": "224", "y": 1031.4, "x": 894.5, "id": "224", "size": 1.0}, {"color": "rgb(153,255,0)", "label": "225", "y": 1444.2, "x": 1468.3, "id": "225", "size": 1.0}, {"color": "rgb(153,255,0)", "label": "226", "y": 838.13, "x": 1523.0, "id": "226", "size": 1.0}, {"color": "rgb(153,255,0)", "label": "227", "y": 1360.4, "x": 1047.5, "id": "227", "size": 1.0}, {"color": "rgb(153,255,0)", "label": "228", "y": 1367.9, "x": 721.51, "id": "228", "size": 1.0}, {"color": "rgb(153,255,0)", "label": "229", "y": 1046.0, "x": 1116.2, "id": "229", "size": 1.0}, {"color": "rgb(153,255,0)", "label": "230", "y": 1441.0, "x": 1940.0, "id": "230", "size": 1.0}, {"color": "rgb(153,255,0)", "label": "231", "y": 1752.0, "x": 812.99, "id": "231", "size": 1.0}, {"color": "rgb(153,255,0)", "label": "232", "y": 1117.1, "x": 707.31, "id": "232", "size": 1.0}, {"color": "rgb(153,255,0)", "label": "233", "y": 1070.6, "x": 856.43, "id": "233", "size": 1.0}, {"color": "rgb(153,255,0)", "label": "234", "y": 1607.2, "x": 995.19, "id": "234", "size": 1.0}, {"color": "rgb(153,255,0)", "label": "235", "y": 1340.8, "x": 1052.2, "id": "235", "size": 1.0}, {"color": "rgb(153,255,0)", "label": "236", "y": 1108.4, "x": 693.55, "id": "236", "size": 1.0}, {"color": "rgb(153,255,0)", "label": "237", "y": 917.9, "x": 601.5, "id": "237", "size": 1.0}, {"color": "rgb(153,255,0)", "label": "238", "y": 1135.0, "x": 1042.9, "id": "238", "size": 1.0}, {"color": "rgb(153,255,0)", "label": "239", "y": 1162.5, "x": 600.0, "id": "239", "size": 1.0}, {"color": "rgb(153,255,0)", "label": "240", "y": 1516.0, "x": 781.0, "id": "240", "size": 1.0}, {"color": "rgb(153,255,0)", "label": "241", "y": 1020.9, "x": 1525.6, "id": "241", "size": 1.0}, {"color": "rgb(153,255,0)", "label": "242", "y": 1471.3, "x": 837.4, "id": "242", "size": 1.0}, {"color": "rgb(153,255,0)", "label": "243", "y": 1045.7, "x": 1405.5, "id": "243", "size": 1.0}, {"color": "rgb(153,255,0)", "label": "244", "y": 1395.4, "x": 2123.6, "id": "244", "size": 1.0}, {"color": "rgb(153,255,0)", "label": "245", "y": 1139.0, "x": 431.75, "id": "245", "size": 1.0}, {"color": "rgb(153,255,0)", "label": "246", "y": 1372.4, "x": 1369.3, "id": "246", "size": 1.0}, {"color": "rgb(153,255,0)", "label": "247", "y": 1585.7, "x": 404.78, "id": "247", "size": 1.0}, {"color": "rgb(153,255,0)", "label": "248", "y": 1330.5, "x": 1008.9, "id": "248", "size": 1.0}, {"color": "rgb(153,255,0)", "label": "249", "y": 1934.5, "x": 2057.4, "id": "249", "size": 1.0}, {"color": "rgb(153,255,0)", "label": "250", "y": 1383.0, "x": 1168.8, "id": "250", "size": 1.0}, {"color": "rgb(153,255,0)", "label": "251", "y": 1631.9, "x": 1216.8, "id": "251", "size": 1.0}, {"color": "rgb(153,255,0)", "label": "252", "y": 1604.0, "x": 717.8, "id": "252", "size": 1.0}, {"color": "rgb(153,255,0)", "label": "253", "y": 1057.1, "x": 1312.9, "id": "253", "size": 1.0}, {"color": "rgb(153,255,0)", "label": "254", "y": 1646.6, "x": 1166.4, "id": "254", "size": 1.0}, {"color": "rgb(153,255,0)", "label": "255", "y": 1484.5, "x": 1289.5, "id": "255", "size": 1.0}, {"color": "rgb(153,255,0)", "label": "256", "y": 959.46, "x": 775.47, "id": "256", "size": 1.0}, {"color": "rgb(153,255,0)", "label": "257", "y": 1405.9, "x": 1113.6, "id": "257", "size": 1.0}, {"color": "rgb(153,255,0)", "label": "258", "y": 1072.7, "x": 687.02, "id": "258", "size": 1.0}, {"color": "rgb(153,255,0)", "label": "259", "y": 1330.2, "x": 1750.3, "id": "259", "size": 1.0}, {"color": "rgb(153,255,0)", "label": "260", "y": 1534.8, "x": 402.82, "id": "260", "size": 1.0}, {"color": "rgb(153,255,0)", "label": "261", "y": 1478.9, "x": 635.65, "id": "261", "size": 1.0}, {"color": "rgb(153,255,0)", "label": "262", "y": 1506.2, "x": 1075.4, "id": "262", "size": 1.0}, {"color": "rgb(153,255,0)", "label": "263", "y": 1008.5, "x": 2031.3, "id": "263", "size": 1.0}, {"color": "rgb(153,255,0)", "label": "264", "y": 1011.6, "x": 1069.9, "id": "264", "size": 1.0}, {"color": "rgb(153,255,0)", "label": "265", "y": 1464.7, "x": 1928.3, "id": "265", "size": 1.0}, {"color": "rgb(153,255,0)", "label": "266", "y": 1210.5, "x": 1171.9, "id": "266", "size": 1.0}, {"color": "rgb(153,255,0)", "label": "268", "y": 746.52, "x": 1732.3, "id": "268", "size": 1.0}, {"color": "rgb(153,255,0)", "label": "269", "y": 1313.2, "x": 1510.5, "id": "269", "size": 1.0}, {"color": "rgb(153,255,0)", "label": "271", "y": 1352.6, "x": 1176.3, "id": "271", "size": 1.0}, {"color": "rgb(153,255,0)", "label": "272", "y": 1129.2, "x": 811.8, "id": "272", "size": 1.0}, {"color": "rgb(153,255,0)", "label": "273", "y": 1202.0, "x": 695.31, "id": "273", "size": 1.0}, {"color": "rgb(153,255,0)", "label": "274", "y": 1254.8, "x": 931.8, "id": "274", "size": 1.0}, {"color": "rgb(153,255,0)", "label": "275", "y": 951.15, "x": 939.55, "id": "275", "size": 1.0}, {"color": "rgb(153,255,0)", "label": "276", "y": 1088.8, "x": 1017.7, "id": "276", "size": 1.0}, {"color": "rgb(153,255,0)", "label": "277", "y": 1504.1, "x": 667.4, "id": "277", "size": 1.0}, {"color": "rgb(153,255,0)", "label": "278", "y": 1330.9, "x": 1110.3, "id": "278", "size": 1.0}, {"color": "rgb(153,255,0)", "label": "279", "y": 999.13, "x": 642.32, "id": "279", "size": 1.0}, {"color": "rgb(153,255,0)", "label": "280", "y": 900.53, "x": 1041.6, "id": "280", "size": 1.0}, {"color": "rgb(153,255,0)", "label": "281", "y": 1767.7, "x": 328.57, "id": "281", "size": 1.0}, {"color": "rgb(153,255,0)", "label": "282", "y": 961.54, "x": 1215.7, "id": "282", "size": 1.0}, {"color": "rgb(153,255,0)", "label": "283", "y": 1993.9, "x": 1070.8, "id": "283", "size": 1.0}, {"color": "rgb(153,255,0)", "label": "284", "y": 1001.2, "x": 917.33, "id": "284", "size": 1.0}, {"color": "rgb(153,255,0)", "label": "285", "y": 1062.3, "x": 584.68, "id": "285", "size": 1.0}, {"color": "rgb(153,255,0)", "label": "286", "y": 996.5, "x": 935.84, "id": "286", "size": 1.0}, {"color": "rgb(153,255,0)", "label": "287", "y": 1470.2, "x": 762.89, "id": "287", "size": 1.0}, {"color": "rgb(153,255,0)", "label": "288", "y": 912.01, "x": 771.59, "id": "288", "size": 1.0}, {"color": "rgb(153,255,0)", "label": "289", "y": 1154.2, "x": 409.87, "id": "289", "size": 1.0}, {"color": "rgb(153,255,0)", "label": "290", "y": 987.45, "x": 1840.3, "id": "290", "size": 1.0}, {"color": "rgb(153,255,0)", "label": "291", "y": 1360.5, "x": 788.39, "id": "291", "size": 1.0}, {"color": "rgb(153,255,0)", "label": "292", "y": 973.74, "x": 1129.2, "id": "292", "size": 1.0}, {"color": "rgb(153,255,0)", "label": "293", "y": 631.43, "x": 696.11, "id": "293", "size": 1.0}, {"color": "rgb(153,255,0)", "label": "294", "y": 1365.2, "x": 1080.1, "id": "294", "size": 1.0}, {"color": "rgb(153,255,0)", "label": "295", "y": 549.19, "x": 781.46, "id": "295", "size": 1.0}, {"color": "rgb(153,255,0)", "label": "296", "y": 1296.6, "x": 1152.7, "id": "296", "size": 1.0}, {"color": "rgb(153,255,0)", "label": "297", "y": 1554.3, "x": 1622.4, "id": "297", "size": 1.0}, {"color": "rgb(153,255,0)", "label": "298", "y": 1199.4, "x": 647.04, "id": "298", "size": 1.0}, {"color": "rgb(153,255,0)", "label": "299", "y": 1480.8, "x": 1025.0, "id": "299", "size": 1.0}, {"color": "rgb(153,255,0)", "label": "300", "y": 1250.8, "x": 792.54, "id": "300", "size": 1.0}, {"color": "rgb(153,255,0)", "label": "301", "y": 1367.9, "x": 393.11, "id": "301", "size": 1.0}, {"color": "rgb(153,255,0)", "label": "302", "y": 1432.8, "x": 492.13, "id": "302", "size": 1.0}, {"color": "rgb(153,255,0)", "label": "303", "y": 1691.4, "x": 1320.6, "id": "303", "size": 1.0}, {"color": "rgb(153,255,0)", "label": "304", "y": 845.6, "x": 1175.8, "id": "304", "size": 1.0}, {"color": "rgb(153,255,0)", "label": "305", "y": 2025.2, "x": 1239.1, "id": "305", "size": 1.0}, {"color": "rgb(153,255,0)", "label": "306", "y": 1044.8, "x": 559.21, "id": "306", "size": 1.0}, {"color": "rgb(153,255,0)", "label": "307", "y": 1302.6, "x": 556.69, "id": "307", "size": 1.0}, {"color": "rgb(153,255,0)", "label": "308", "y": 952.03, "x": 348.73, "id": "308", "size": 1.0}, {"color": "rgb(153,255,0)", "label": "309", "y": 1799.9, "x": 914.99, "id": "309", "size": 1.0}, {"color": "rgb(153,255,0)", "label": "310", "y": 1188.4, "x": 1313.5, "id": "310", "size": 1.0}, {"color": "rgb(153,255,0)", "label": "311", "y": 1272.0, "x": 467.85, "id": "311", "size": 1.0}, {"color": "rgb(153,255,0)", "label": "312", "y": 1276.6, "x": 1064.3, "id": "312", "size": 1.0}, {"color": "rgb(153,255,0)", "label": "313", "y": 1437.0, "x": 583.97, "id": "313", "size": 1.0}, {"color": "rgb(153,255,0)", "label": "314", "y": 1309.2, "x": 975.54, "id": "314", "size": 1.0}, {"color": "rgb(153,255,0)", "label": "315", "y": 1500.6, "x": 568.1, "id": "315", "size": 1.0}, {"color": "rgb(153,255,0)", "label": "316", "y": 1729.0, "x": 769.46, "id": "316", "size": 1.0}, {"color": "rgb(153,255,0)", "label": "317", "y": 1624.0, "x": 901.25, "id": "317", "size": 1.0}, {"color": "rgb(153,255,0)", "label": "318", "y": 1321.0, "x": 869.46, "id": "318", "size": 1.0}, {"color": "rgb(153,255,0)", "label": "319", "y": 1411.5, "x": 793.33, "id": "319", "size": 1.0}, {"color": "rgb(153,255,0)", "label": "320", "y": 1336.1, "x": 928.67, "id": "320", "size": 1.0}, {"color": "rgb(153,255,0)", "label": "321", "y": 1817.5, "x": 1120.2, "id": "321", "size": 1.0}, {"color": "rgb(153,255,0)", "label": "322", "y": 1136.6, "x": 940.9, "id": "322", "size": 1.0}, {"color": "rgb(153,255,0)", "label": "323", "y": 1313.1, "x": 1064.5, "id": "323", "size": 1.0}, {"color": "rgb(153,255,0)", "label": "324", "y": 1208.9, "x": 1561.1, "id": "324", "size": 1.0}, {"color": "rgb(153,255,0)", "label": "325", "y": 1516.8, "x": 524.04, "id": "325", "size": 1.0}, {"color": "rgb(153,255,0)", "label": "326", "y": 1438.9, "x": 672.27, "id": "326", "size": 1.0}, {"color": "rgb(153,255,0)", "label": "327", "y": 1379.8, "x": 1135.8, "id": "327", "size": 1.0}, {"color": "rgb(153,255,0)", "label": "328", "y": 934.59, "x": 1159.8, "id": "328", "size": 1.0}, {"color": "rgb(153,255,0)", "label": "329", "y": 1250.8, "x": 917.09, "id": "329", "size": 1.0}, {"color": "rgb(153,255,0)", "label": "330", "y": 1145.4, "x": 831.1, "id": "330", "size": 1.0}, {"color": "rgb(153,255,0)", "label": "331", "y": 1214.0, "x": 783.56, "id": "331", "size": 1.0}, {"color": "rgb(153,255,0)", "label": "332", "y": 1591.0, "x": 1031.4, "id": "332", "size": 1.0}, {"color": "rgb(153,255,0)", "label": "333", "y": 821.58, "x": 1352.7, "id": "333", "size": 1.0}, {"color": "rgb(153,255,0)", "label": "334", "y": 1758.9, "x": 890.43, "id": "334", "size": 1.0}, {"color": "rgb(153,255,0)", "label": "335", "y": 1800.7, "x": 1056.1, "id": "335", "size": 1.0}, {"color": "rgb(153,255,0)", "label": "336", "y": 724.51, "x": 658.42, "id": "336", "size": 1.0}, {"color": "rgb(153,255,0)", "label": "337", "y": 1770.1, "x": 1244.3, "id": "337", "size": 1.0}, {"color": "rgb(153,255,0)", "label": "338", "y": 1253.8, "x": 1677.9, "id": "338", "size": 1.0}, {"color": "rgb(153,255,0)", "label": "339", "y": 1267.4, "x": 766.58, "id": "339", "size": 1.0}, {"color": "rgb(153,255,0)", "label": "340", "y": 1346.9, "x": 670.16, "id": "340", "size": 1.0}, {"color": "rgb(153,255,0)", "label": "341", "y": 1345.0, "x": 448.91, "id": "341", "size": 1.0}, {"color": "rgb(153,255,0)", "label": "342", "y": 1389.6, "x": 1224.1, "id": "342", "size": 1.0}, {"color": "rgb(153,255,0)", "label": "343", "y": 933.67, "x": 1340.6, "id": "343", "size": 1.0}, {"color": "rgb(153,255,0)", "label": "344", "y": 1703.6, "x": 952.15, "id": "344", "size": 1.0}, {"color": "rgb(153,255,0)", "label": "345", "y": 1191.5, "x": 1330.8, "id": "345", "size": 1.0}, {"color": "rgb(153,255,0)", "label": "346", "y": 981.16, "x": 544.72, "id": "346", "size": 1.0}, {"color": "rgb(153,255,0)", "label": "347", "y": 1729.4, "x": 812.45, "id": "347", "size": 1.0}, {"color": "rgb(153,255,0)", "label": "348", "y": 992.41, "x": 200.59, "id": "348", "size": 1.0}, {"color": "rgb(153,255,0)", "label": "349", "y": 1929.2, "x": 1062.0, "id": "349", "size": 1.0}, {"color": "rgb(153,255,0)", "label": "350", "y": 1698.4, "x": 659.21, "id": "350", "size": 1.0}, {"color": "rgb(153,255,0)", "label": "351", "y": 1366.9, "x": 534.45, "id": "351", "size": 1.0}, {"color": "rgb(153,255,0)", "label": "352", "y": 1868.9, "x": 1430.5, "id": "352", "size": 1.0}, {"color": "rgb(153,255,0)", "label": "353", "y": 1491.2, "x": 572.39, "id": "353", "size": 1.0}, {"color": "rgb(153,255,0)", "label": "354", "y": 1174.4, "x": 492.58, "id": "354", "size": 1.0}, {"color": "rgb(153,255,0)", "label": "355", "y": 1007.5, "x": 1038.3, "id": "355", "size": 1.0}, {"color": "rgb(153,255,0)", "label": "356", "y": 1551.6, "x": 1716.7, "id": "356", "size": 1.0}, {"color": "rgb(153,255,0)", "label": "357", "y": 1731.0, "x": 1514.8, "id": "357", "size": 1.0}, {"color": "rgb(153,255,0)", "label": "358", "y": 920.37, "x": 805.83, "id": "358", "size": 1.0}, {"color": "rgb(153,255,0)", "label": "359", "y": 1196.4, "x": 1216.3, "id": "359", "size": 1.0}, {"color": "rgb(153,255,0)", "label": "360", "y": 1094.8, "x": 2213.7, "id": "360", "size": 1.0}, {"color": "rgb(153,255,0)", "label": "361", "y": 18.0, "x": 2396.4, "id": "361", "size": 1.0}, {"color": "rgb(153,255,0)", "label": "362", "y": 1751.8, "x": 873.36, "id": "362", "size": 1.0}, {"color": "rgb(153,255,0)", "label": "363", "y": 888.08, "x": 533.74, "id": "363", "size": 1.0}, {"color": "rgb(153,255,0)", "label": "364", "y": 715.85, "x": 2120.8, "id": "364", "size": 1.0}, {"color": "rgb(153,255,0)", "label": "365", "y": 1185.9, "x": 151.45, "id": "365", "size": 1.0}, {"color": "rgb(153,255,0)", "label": "366", "y": 1164.3, "x": 249.25, "id": "366", "size": 1.0}, {"color": "rgb(153,255,0)", "label": "367", "y": 1061.0, "x": 873.09, "id": "367", "size": 1.0}, {"color": "rgb(153,255,0)", "label": "368", "y": 1288.3, "x": 601.72, "id": "368", "size": 1.0}, {"color": "rgb(153,255,0)", "label": "369", "y": 1047.4, "x": 1365.8, "id": "369", "size": 1.0}, {"color": "rgb(153,255,0)", "label": "370", "y": 1409.9, "x": 849.91, "id": "370", "size": 1.0}, {"color": "rgb(153,255,0)", "label": "371", "y": 1750.0, "x": 590.13, "id": "371", "size": 1.0}, {"color": "rgb(153,255,0)", "label": "372", "y": 1180.6, "x": 1670.8, "id": "372", "size": 1.0}, {"color": "rgb(153,255,0)", "label": "373", "y": 1288.4, "x": 1295.4, "id": "373", "size": 1.0}, {"color": "rgb(153,255,0)", "label": "374", "y": 1363.7, "x": 277.86, "id": "374", "size": 1.0}, {"color": "rgb(153,255,0)", "label": "375", "y": 748.42, "x": 1406.0, "id": "375", "size": 1.0}, {"color": "rgb(153,255,0)", "label": "376", "y": 1231.0, "x": 1082.0, "id": "376", "size": 1.0}, {"color": "rgb(153,255,0)", "label": "377", "y": 1585.0, "x": 349.74, "id": "377", "size": 1.0}, {"color": "rgb(153,255,0)", "label": "378", "y": 1338.6, "x": 1153.7, "id": "378", "size": 1.0}, {"color": "rgb(153,255,0)", "label": "379", "y": 1276.5, "x": 686.06, "id": "379", "size": 1.0}, {"color": "rgb(153,255,0)", "label": "380", "y": 1168.2, "x": 1296.1, "id": "380", "size": 1.0}, {"color": "rgb(153,255,0)", "label": "381", "y": 1458.7, "x": 488.93, "id": "381", "size": 1.0}, {"color": "rgb(153,255,0)", "label": "382", "y": 975.56, "x": 1162.2, "id": "382", "size": 1.0}, {"color": "rgb(153,255,0)", "label": "383", "y": 1501.3, "x": 384.67, "id": "383", "size": 1.0}, {"color": "rgb(153,255,0)", "label": "384", "y": 1590.0, "x": 604.06, "id": "384", "size": 1.0}, {"color": "rgb(153,255,0)", "label": "385", "y": 1390.1, "x": 976.29, "id": "385", "size": 1.0}, {"color": "rgb(153,255,0)", "label": "386", "y": 1640.6, "x": 440.92, "id": "386", "size": 1.0}, {"color": "rgb(153,255,0)", "label": "387", "y": 1164.5, "x": 940.35, "id": "387", "size": 1.0}, {"color": "rgb(153,255,0)", "label": "388", "y": 938.17, "x": 783.33, "id": "388", "size": 1.0}, {"color": "rgb(153,255,0)", "label": "389", "y": 1633.3, "x": 614.85, "id": "389", "size": 1.0}, {"color": "rgb(153,255,0)", "label": "390", "y": 125.29, "x": 1682.5, "id": "390", "size": 1.0}, {"color": "rgb(153,255,0)", "label": "391", "y": 757.24, "x": 923.81, "id": "391", "size": 1.0}, {"color": "rgb(153,255,0)", "label": "392", "y": 1740.9, "x": 1335.5, "id": "392", "size": 1.0}, {"color": "rgb(153,255,0)", "label": "393", "y": 1088.3, "x": 1949.1, "id": "393", "size": 1.0}, {"color": "rgb(153,255,0)", "label": "394", "y": 1044.6, "x": 1532.5, "id": "394", "size": 1.0}, {"color": "rgb(153,255,0)", "label": "395", "y": 1186.6, "x": 1155.6, "id": "395", "size": 1.0}, {"color": "rgb(153,255,0)", "label": "396", "y": 1021.2, "x": 706.08, "id": "396", "size": 1.0}, {"color": "rgb(153,255,0)", "label": "397", "y": 717.73, "x": 1054.9, "id": "397", "size": 1.0}, {"color": "rgb(153,255,0)", "label": "398", "y": 712.51, "x": 793.85, "id": "398", "size": 1.0}, {"color": "rgb(153,255,0)", "label": "399", "y": 1134.6, "x": 523.08, "id": "399", "size": 1.0}, {"color": "rgb(153,255,0)", "label": "400", "y": 1266.9, "x": 2128.8, "id": "400", "size": 1.0}, {"color": "rgb(153,255,0)", "label": "401", "y": 1053.5, "x": 802.09, "id": "401", "size": 1.0}, {"color": "rgb(153,255,0)", "label": "402", "y": 1690.3, "x": 481.84, "id": "402", "size": 1.0}, {"color": "rgb(153,255,0)", "label": "403", "y": 1364.3, "x": 757.79, "id": "403", "size": 1.0}, {"color": "rgb(153,255,0)", "label": "404", "y": 1523.0, "x": 905.3, "id": "404", "size": 1.0}, {"color": "rgb(153,255,0)", "label": "405", "y": 1717.6, "x": 1073.3, "id": "405", "size": 1.0}, {"color": "rgb(153,255,0)", "label": "406", "y": 1376.0, "x": 700.31, "id": "406", "size": 1.0}, {"color": "rgb(153,255,0)", "label": "407", "y": 1414.5, "x": 736.14, "id": "407", "size": 1.0}, {"color": "rgb(153,255,0)", "label": "408", "y": 1050.5, "x": 1274.1, "id": "408", "size": 1.0}, {"color": "rgb(153,255,0)", "label": "409", "y": 1374.7, "x": 615.23, "id": "409", "size": 1.0}, {"color": "rgb(153,255,0)", "label": "410", "y": 692.67, "x": 1318.6, "id": "410", "size": 1.0}, {"color": "rgb(153,255,0)", "label": "411", "y": 1944.3, "x": 2185.0, "id": "411", "size": 1.0}, {"color": "rgb(153,255,0)", "label": "412", "y": 1520.1, "x": 317.18, "id": "412", "size": 1.0}, {"color": "rgb(153,255,0)", "label": "413", "y": 1336.7, "x": 2272.4, "id": "413", "size": 1.0}, {"color": "rgb(153,255,0)", "label": "414", "y": 1838.6, "x": 2836.9, "id": "414", "size": 1.0}, {"color": "rgb(153,255,0)", "label": "415", "y": 1750.3, "x": 1401.1, "id": "415", "size": 1.0}, {"color": "rgb(153,255,0)", "label": "416", "y": 990.8, "x": 1014.5, "id": "416", "size": 1.0}, {"color": "rgb(153,255,0)", "label": "417", "y": 1144.9, "x": 258.67, "id": "417", "size": 1.0}, {"color": "rgb(153,255,0)", "label": "418", "y": 1576.5, "x": 361.59, "id": "418", "size": 1.0}, {"color": "rgb(153,255,0)", "label": "419", "y": 1311.6, "x": 2025.0, "id": "419", "size": 1.0}, {"color": "rgb(153,255,0)", "label": "420", "y": 1121.6, "x": 1005.7, "id": "420", "size": 1.0}, {"color": "rgb(153,255,0)", "label": "421", "y": 808.31, "x": 1097.6, "id": "421", "size": 1.0}, {"color": "rgb(153,255,0)", "label": "422", "y": 1073.4, "x": 551.93, "id": "422", "size": 1.0}, {"color": "rgb(153,255,0)", "label": "423", "y": 1205.3, "x": 2256.2, "id": "423", "size": 1.0}, {"color": "rgb(153,255,0)", "label": "424", "y": 1070.9, "x": 946.09, "id": "424", "size": 1.0}, {"color": "rgb(153,255,0)", "label": "425", "y": 881.51, "x": 1406.0, "id": "425", "size": 1.0}, {"color": "rgb(153,255,0)", "label": "426", "y": 1049.7, "x": 1227.8, "id": "426", "size": 1.0}, {"color": "rgb(153,255,0)", "label": "427", "y": 1662.2, "x": 1092.1, "id": "427", "size": 1.0}, {"color": "rgb(153,255,0)", "label": "428", "y": 1263.8, "x": 815.68, "id": "428", "size": 1.0}, {"color": "rgb(153,255,0)", "label": "429", "y": 949.39, "x": 925.13, "id": "429", "size": 1.0}, {"color": "rgb(153,255,0)", "label": "430", "y": 1778.1, "x": 1015.6, "id": "430", "size": 1.0}, {"color": "rgb(153,255,0)", "label": "431", "y": 1349.5, "x": 422.65, "id": "431", "size": 1.0}, {"color": "rgb(153,255,0)", "label": "432", "y": 1690.9, "x": 813.47, "id": "432", "size": 1.0}, {"color": "rgb(153,255,0)", "label": "433", "y": 1131.4, "x": 545.17, "id": "433", "size": 1.0}, {"color": "rgb(153,255,0)", "label": "434", "y": 1085.4, "x": 1110.6, "id": "434", "size": 1.0}, {"color": "rgb(153,255,0)", "label": "435", "y": 1243.5, "x": 1637.9, "id": "435", "size": 1.0}, {"color": "rgb(153,255,0)", "label": "436", "y": 1549.7, "x": 1150.6, "id": "436", "size": 1.0}, {"color": "rgb(153,255,0)", "label": "437", "y": 1097.2, "x": 742.28, "id": "437", "size": 1.0}, {"color": "rgb(153,255,0)", "label": "438", "y": 849.64, "x": 796.12, "id": "438", "size": 1.0}, {"color": "rgb(153,255,0)", "label": "439", "y": 1311.3, "x": 817.41, "id": "439", "size": 1.0}, {"color": "rgb(153,255,0)", "label": "440", "y": 1440.4, "x": 367.69, "id": "440", "size": 1.0}, {"color": "rgb(153,255,0)", "label": "441", "y": 952.4, "x": 727.18, "id": "441", "size": 1.0}, {"color": "rgb(153,255,0)", "label": "442", "y": 1510.4, "x": 1363.7, "id": "442", "size": 1.0}, {"color": "rgb(153,255,0)", "label": "443", "y": 1423.7, "x": 1012.1, "id": "443", "size": 1.0}, {"color": "rgb(153,255,0)", "label": "444", "y": 1349.2, "x": 1512.4, "id": "444", "size": 1.0}, {"color": "rgb(153,255,0)", "label": "445", "y": 1302.6, "x": 658.37, "id": "445", "size": 1.0}, {"color": "rgb(153,255,0)", "label": "446", "y": 1581.8, "x": 1429.6, "id": "446", "size": 1.0}, {"color": "rgb(153,255,0)", "label": "447", "y": 1476.1, "x": 2575.9, "id": "447", "size": 1.0}, {"color": "rgb(153,255,0)", "label": "448", "y": 1258.5, "x": 1066.5, "id": "448", "size": 1.0}, {"color": "rgb(153,255,0)", "label": "449", "y": 976.81, "x": 1988.7, "id": "449", "size": 1.0}, {"color": "rgb(153,255,0)", "label": "450", "y": 1218.3, "x": 540.51, "id": "450", "size": 1.0}, {"color": "rgb(153,255,0)", "label": "451", "y": 1479.7, "x": 1247.6, "id": "451", "size": 1.0}, {"color": "rgb(153,255,0)", "label": "452", "y": 733.22, "x": 981.4, "id": "452", "size": 1.0}, {"color": "rgb(153,255,0)", "label": "453", "y": 1563.3, "x": 865.35, "id": "453", "size": 1.0}, {"color": "rgb(153,255,0)", "label": "454", "y": 1571.4, "x": 711.78, "id": "454", "size": 1.0}, {"color": "rgb(153,255,0)", "label": "455", "y": 1021.4, "x": 419.25, "id": "455", "size": 1.0}, {"color": "rgb(153,255,0)", "label": "456", "y": 1776.3, "x": 1919.1, "id": "456", "size": 1.0}, {"color": "rgb(153,255,0)", "label": "457", "y": 1316.4, "x": 408.04, "id": "457", "size": 1.0}, {"color": "rgb(153,255,0)", "label": "458", "y": 1049.7, "x": 207.77, "id": "458", "size": 1.0}, {"color": "rgb(153,255,0)", "label": "459", "y": 1818.0, "x": 835.74, "id": "459", "size": 1.0}, {"color": "rgb(153,255,0)", "label": "460", "y": 867.03, "x": 1048.8, "id": "460", "size": 1.0}, {"color": "rgb(153,255,0)", "label": "461", "y": 1034.9, "x": 1030.1, "id": "461", "size": 1.0}, {"color": "rgb(153,255,0)", "label": "462", "y": 1195.8, "x": 387.02, "id": "462", "size": 1.0}, {"color": "rgb(153,255,0)", "label": "463", "y": 1247.2, "x": 294.43, "id": "463", "size": 1.0}, {"color": "rgb(153,255,0)", "label": "464", "y": 1718.4, "x": 1135.4, "id": "464", "size": 1.0}, {"color": "rgb(153,255,0)", "label": "465", "y": 789.56, "x": 906.64, "id": "465", "size": 1.0}, {"color": "rgb(153,255,0)", "label": "466", "y": 773.17, "x": 1058.6, "id": "466", "size": 1.0}, {"color": "rgb(153,255,0)", "label": "467", "y": 1274.4, "x": 1354.8, "id": "467", "size": 1.0}, {"color": "rgb(153,255,0)", "label": "468", "y": 786.27, "x": 2161.3, "id": "468", "size": 1.0}, {"color": "rgb(153,255,0)", "label": "469", "y": 1320.2, "x": 1473.5, "id": "469", "size": 1.0}, {"color": "rgb(153,255,0)", "label": "470", "y": 1743.7, "x": 906.58, "id": "470", "size": 1.0}, {"color": "rgb(153,255,0)", "label": "471", "y": 788.42, "x": 1010.7, "id": "471", "size": 1.0}, {"color": "rgb(153,255,0)", "label": "472", "y": 1733.5, "x": 424.72, "id": "472", "size": 1.0}, {"color": "rgb(153,255,0)", "label": "473", "y": 1008.1, "x": 689.76, "id": "473", "size": 1.0}, {"color": "rgb(153,255,0)", "label": "474", "y": 1236.8, "x": 1285.2, "id": "474", "size": 1.0}, {"color": "rgb(153,255,0)", "label": "475", "y": 1153.0, "x": 481.28, "id": "475", "size": 1.0}, {"color": "rgb(153,255,0)", "label": "476", "y": 1485.1, "x": 1107.2, "id": "476", "size": 1.0}, {"color": "rgb(153,255,0)", "label": "477", "y": 1214.9, "x": 811.84, "id": "477", "size": 1.0}, {"color": "rgb(153,255,0)", "label": "478", "y": 1379.7, "x": 1501.8, "id": "478", "size": 1.0}, {"color": "rgb(153,255,0)", "label": "479", "y": 999.3, "x": 503.85, "id": "479", "size": 1.0}, {"color": "rgb(153,255,0)", "label": "480", "y": 1668.2, "x": 674.97, "id": "480", "size": 1.0}, {"color": "rgb(153,255,0)", "label": "481", "y": 1785.8, "x": 870.84, "id": "481", "size": 1.0}, {"color": "rgb(153,255,0)", "label": "482", "y": 1479.5, "x": 689.1, "id": "482", "size": 1.0}, {"color": "rgb(153,255,0)", "label": "483", "y": 991.43, "x": 478.77, "id": "483", "size": 1.0}, {"color": "rgb(153,255,0)", "label": "484", "y": 1013.9, "x": 1106.2, "id": "484", "size": 1.0}, {"color": "rgb(153,255,0)", "label": "485", "y": 1190.2, "x": 885.66, "id": "485", "size": 1.0}, {"color": "rgb(153,255,0)", "label": "486", "y": 1177.2, "x": 950.41, "id": "486", "size": 1.0}, {"color": "rgb(153,255,0)", "label": "487", "y": 1951.5, "x": 679.5, "id": "487", "size": 1.0}, {"color": "rgb(153,255,0)", "label": "488", "y": 1787.4, "x": 768.34, "id": "488", "size": 1.0}, {"color": "rgb(153,255,0)", "label": "489", "y": 1633.5, "x": 947.89, "id": "489", "size": 1.0}, {"color": "rgb(153,255,0)", "label": "490", "y": 1532.7, "x": 1059.7, "id": "490", "size": 1.0}, {"color": "rgb(153,255,0)", "label": "491", "y": 1644.8, "x": 926.64, "id": "491", "size": 1.0}, {"color": "rgb(153,255,0)", "label": "492", "y": 871.13, "x": 2212.6, "id": "492", "size": 1.0}, {"color": "rgb(153,255,0)", "label": "493", "y": 1132.9, "x": 1080.1, "id": "493", "size": 1.0}, {"color": "rgb(153,255,0)", "label": "494", "y": 1550.7, "x": 1335.6, "id": "494", "size": 1.0}, {"color": "rgb(153,255,0)", "label": "495", "y": 961.19, "x": 659.56, "id": "495", "size": 1.0}, {"color": "rgb(153,255,0)", "label": "496", "y": 1351.4, "x": 1248.6, "id": "496", "size": 1.0}, {"color": "rgb(153,255,0)", "label": "497", "y": 666.75, "x": 871.51, "id": "497", "size": 1.0}, {"color": "rgb(153,255,0)", "label": "498", "y": 1602.1, "x": 622.47, "id": "498", "size": 1.0}, {"color": "rgb(153,255,0)", "label": "499", "y": 1765.8, "x": 537.63, "id": "499", "size": 1.0}, {"color": "rgb(153,255,0)", "label": "500", "y": 1548.5, "x": 513.51, "id": "500", "size": 1.0}, {"color": "rgb(153,255,0)", "label": "501", "y": 607.3, "x": 1438.0, "id": "501", "size": 1.0}, {"color": "rgb(153,255,0)", "label": "502", "y": 1602.3, "x": 1012.4, "id": "502", "size": 1.0}, {"color": "rgb(153,255,0)", "label": "503", "y": 1315.9, "x": 1318.3, "id": "503", "size": 1.0}, {"color": "rgb(153,255,0)", "label": "504", "y": 1651.4, "x": 847.33, "id": "504", "size": 1.0}, {"color": "rgb(153,255,0)", "label": "505", "y": 1169.0, "x": 922.51, "id": "505", "size": 1.0}, {"color": "rgb(153,255,0)", "label": "506", "y": 839.9, "x": 690.41, "id": "506", "size": 1.0}, {"color": "rgb(153,255,0)", "label": "507", "y": 741.57, "x": 491.69, "id": "507", "size": 1.0}, {"color": "rgb(153,255,0)", "label": "508", "y": 974.34, "x": 450.72, "id": "508", "size": 1.0}, {"color": "rgb(153,255,0)", "label": "509", "y": 1088.2, "x": 1312.5, "id": "509", "size": 1.0}, {"color": "rgb(153,255,0)", "label": "510", "y": 1155.1, "x": 987.49, "id": "510", "size": 1.0}, {"color": "rgb(153,255,0)", "label": "511", "y": 1044.5, "x": 778.08, "id": "511", "size": 1.0}, {"color": "rgb(153,255,0)", "label": "512", "y": 1386.8, "x": 1543.6, "id": "512", "size": 1.0}, {"color": "rgb(153,255,0)", "label": "513", "y": 907.15, "x": 985.62, "id": "513", "size": 1.0}, {"color": "rgb(153,255,0)", "label": "514", "y": 874.4, "x": 835.94, "id": "514", "size": 1.0}, {"color": "rgb(153,255,0)", "label": "515", "y": 1406.2, "x": 726.85, "id": "515", "size": 1.0}, {"color": "rgb(153,255,0)", "label": "516", "y": 1538.1, "x": 1225.1, "id": "516", "size": 1.0}, {"color": "rgb(153,255,0)", "label": "517", "y": 2030.2, "x": 888.51, "id": "517", "size": 1.0}, {"color": "rgb(153,255,0)", "label": "518", "y": 737.78, "x": 811.98, "id": "518", "size": 1.0}, {"color": "rgb(153,255,0)", "label": "519", "y": 1282.6, "x": 757.36, "id": "519", "size": 1.0}, {"color": "rgb(153,255,0)", "label": "520", "y": 1406.5, "x": 630.41, "id": "520", "size": 1.0}, {"color": "rgb(153,255,0)", "label": "521", "y": 1704.9, "x": 1239.2, "id": "521", "size": 1.0}, {"color": "rgb(153,255,0)", "label": "522", "y": 960.88, "x": 1052.6, "id": "522", "size": 1.0}, {"color": "rgb(153,255,0)", "label": "523", "y": 1230.2, "x": 355.87, "id": "523", "size": 1.0}, {"color": "rgb(153,255,0)", "label": "524", "y": 1207.9, "x": 758.09, "id": "524", "size": 1.0}, {"color": "rgb(153,255,0)", "label": "525", "y": 1416.4, "x": 988.61, "id": "525", "size": 1.0}, {"color": "rgb(153,255,0)", "label": "526", "y": 1186.7, "x": 1380.5, "id": "526", "size": 1.0}, {"color": "rgb(153,255,0)", "label": "527", "y": 1304.9, "x": 669.9, "id": "527", "size": 1.0}, {"color": "rgb(153,255,0)", "label": "528", "y": 816.86, "x": 849.24, "id": "528", "size": 1.0}, {"color": "rgb(153,255,0)", "label": "529", "y": 1189.0, "x": 1036.9, "id": "529", "size": 1.0}, {"color": "rgb(153,255,0)", "label": "530", "y": 1067.1, "x": 1165.0, "id": "530", "size": 1.0}, {"color": "rgb(153,255,0)", "label": "531", "y": 937.89, "x": 1560.6, "id": "531", "size": 1.0}, {"color": "rgb(153,255,0)", "label": "532", "y": 1294.6, "x": 487.45, "id": "532", "size": 1.0}, {"color": "rgb(153,255,0)", "label": "533", "y": 1401.0, "x": 922.57, "id": "533", "size": 1.0}, {"color": "rgb(153,255,0)", "label": "534", "y": 1191.1, "x": 27.0, "id": "534", "size": 1.0}, {"color": "rgb(153,255,0)", "label": "535", "y": 1344.0, "x": 788.92, "id": "535", "size": 1.0}, {"color": "rgb(153,255,0)", "label": "536", "y": 1242.8, "x": 1334.1, "id": "536", "size": 1.0}, {"color": "rgb(153,255,0)", "label": "537", "y": 1323.0, "x": 727.81, "id": "537", "size": 1.0}, {"color": "rgb(153,255,0)", "label": "538", "y": 811.51, "x": 905.44, "id": "538", "size": 1.0}, {"color": "rgb(153,255,0)", "label": "539", "y": 1351.1, "x": 1289.8, "id": "539", "size": 1.0}, {"color": "rgb(153,255,0)", "label": "540", "y": 1252.4, "x": 1251.1, "id": "540", "size": 1.0}, {"color": "rgb(153,255,0)", "label": "541", "y": 1446.5, "x": 201.11, "id": "541", "size": 1.0}, {"color": "rgb(153,255,0)", "label": "542", "y": 1329.1, "x": 236.47, "id": "542", "size": 1.0}, {"color": "rgb(153,255,0)", "label": "543", "y": 1057.1, "x": 1583.7, "id": "543", "size": 1.0}, {"color": "rgb(153,255,0)", "label": "544", "y": 1744.5, "x": 727.95, "id": "544", "size": 1.0}, {"color": "rgb(153,255,0)", "label": "545", "y": 707.47, "x": 1343.9, "id": "545", "size": 1.0}, {"color": "rgb(153,255,0)", "label": "546", "y": 1172.2, "x": 1057.7, "id": "546", "size": 1.0}, {"color": "rgb(153,255,0)", "label": "547", "y": 1225.3, "x": 1152.3, "id": "547", "size": 1.0}, {"color": "rgb(153,255,0)", "label": "548", "y": 874.97, "x": 1215.7, "id": "548", "size": 1.0}, {"color": "rgb(153,255,0)", "label": "549", "y": 887.75, "x": 874.48, "id": "549", "size": 1.0}, {"color": "rgb(153,255,0)", "label": "550", "y": 901.77, "x": 1986.9, "id": "550", "size": 1.0}, {"color": "rgb(153,255,0)", "label": "551", "y": 506.56, "x": 2026.6, "id": "551", "size": 1.0}, {"color": "rgb(153,255,0)", "label": "552", "y": 1684.2, "x": 715.23, "id": "552", "size": 1.0}, {"color": "rgb(153,255,0)", "label": "553", "y": 1402.0, "x": 1043.2, "id": "553", "size": 1.0}, {"color": "rgb(153,255,0)", "label": "554", "y": 1519.0, "x": 1388.4, "id": "554", "size": 1.0}, {"color": "rgb(153,255,0)", "label": "555", "y": 1021.2, "x": 1053.0, "id": "555", "size": 1.0}, {"color": "rgb(153,255,0)", "label": "556", "y": 1598.6, "x": 876.03, "id": "556", "size": 1.0}, {"color": "rgb(153,255,0)", "label": "557", "y": 1452.5, "x": 941.46, "id": "557", "size": 1.0}, {"color": "rgb(153,255,0)", "label": "558", "y": 1808.7, "x": 1311.9, "id": "558", "size": 1.0}, {"color": "rgb(153,255,0)", "label": "559", "y": 776.55, "x": 618.81, "id": "559", "size": 1.0}, {"color": "rgb(153,255,0)", "label": "560", "y": 931.68, "x": 1047.9, "id": "560", "size": 1.0}, {"color": "rgb(153,255,0)", "label": "561", "y": 802.61, "x": 549.28, "id": "561", "size": 1.0}, {"color": "rgb(153,255,0)", "label": "562", "y": 1902.6, "x": 1058.5, "id": "562", "size": 1.0}, {"color": "rgb(153,255,0)", "label": "563", "y": 1096.3, "x": 464.5, "id": "563", "size": 1.0}, {"color": "rgb(153,255,0)", "label": "564", "y": 846.86, "x": 1420.3, "id": "564", "size": 1.0}, {"color": "rgb(153,255,0)", "label": "565", "y": 252.96, "x": 2204.2, "id": "565", "size": 1.0}, {"color": "rgb(153,255,0)", "label": "566", "y": 1504.1, "x": 753.25, "id": "566", "size": 1.0}, {"color": "rgb(153,255,0)", "label": "567", "y": 1283.6, "x": 233.49, "id": "567", "size": 1.0}, {"color": "rgb(153,255,0)", "label": "568", "y": 1210.2, "x": 567.85, "id": "568", "size": 1.0}, {"color": "rgb(153,255,0)", "label": "569", "y": 1685.9, "x": 581.86, "id": "569", "size": 1.0}, {"color": "rgb(153,255,0)", "label": "570", "y": 1128.6, "x": 1093.7, "id": "570", "size": 1.0}, {"color": "rgb(153,255,0)", "label": "571", "y": 1580.4, "x": 738.91, "id": "571", "size": 1.0}, {"color": "rgb(153,255,0)", "label": "572", "y": 1035.8, "x": 1252.2, "id": "572", "size": 1.0}, {"color": "rgb(153,255,0)", "label": "573", "y": 1140.4, "x": 1968.8, "id": "573", "size": 1.0}, {"color": "rgb(153,255,0)", "label": "574", "y": 1308.0, "x": 941.78, "id": "574", "size": 1.0}, {"color": "rgb(153,255,0)", "label": "575", "y": 1724.4, "x": 590.3, "id": "575", "size": 1.0}, {"color": "rgb(153,255,0)", "label": "576", "y": 1505.9, "x": 518.45, "id": "576", "size": 1.0}, {"color": "rgb(153,255,0)", "label": "577", "y": 1665.8, "x": 1411.5, "id": "577", "size": 1.0}, {"color": "rgb(153,255,0)", "label": "578", "y": 1288.0, "x": 379.57, "id": "578", "size": 1.0}, {"color": "rgb(153,255,0)", "label": "579", "y": 1384.0, "x": 515.5, "id": "579", "size": 1.0}, {"color": "rgb(153,255,0)", "label": "580", "y": 1846.4, "x": 696.52, "id": "580", "size": 1.0}, {"color": "rgb(153,255,0)", "label": "581", "y": 1376.2, "x": 1665.7, "id": "581", "size": 1.0}, {"color": "rgb(153,255,0)", "label": "582", "y": 1164.7, "x": 1263.5, "id": "582", "size": 1.0}, {"color": "rgb(153,255,0)", "label": "583", "y": 1187.6, "x": 511.71, "id": "583", "size": 1.0}, {"color": "rgb(153,255,0)", "label": "584", "y": 884.01, "x": 1119.8, "id": "584", "size": 1.0}, {"color": "rgb(153,255,0)", "label": "585", "y": 1612.6, "x": 1073.4, "id": "585", "size": 1.0}, {"color": "rgb(153,255,0)", "label": "586", "y": 768.64, "x": 1038.3, "id": "586", "size": 1.0}, {"color": "rgb(153,255,0)", "label": "587", "y": 1274.3, "x": 717.16, "id": "587", "size": 1.0}, {"color": "rgb(153,255,0)", "label": "588", "y": 1254.0, "x": 2005.7, "id": "588", "size": 1.0}, {"color": "rgb(153,255,0)", "label": "589", "y": 893.2, "x": 1636.3, "id": "589", "size": 1.0}, {"color": "rgb(153,255,0)", "label": "590", "y": 1250.1, "x": 979.52, "id": "590", "size": 1.0}, {"color": "rgb(153,255,0)", "label": "591", "y": 1652.3, "x": 1895.9, "id": "591", "size": 1.0}, {"color": "rgb(153,255,0)", "label": "592", "y": 893.9, "x": 2101.2, "id": "592", "size": 1.0}, {"color": "rgb(153,255,0)", "label": "593", "y": 1769.0, "x": 831.98, "id": "593", "size": 1.0}, {"color": "rgb(153,255,0)", "label": "594", "y": 1501.8, "x": 848.47, "id": "594", "size": 1.0}, {"color": "rgb(153,255,0)", "label": "595", "y": 1268.8, "x": 434.04, "id": "595", "size": 1.0}, {"color": "rgb(153,255,0)", "label": "596", "y": 1187.4, "x": 726.62, "id": "596", "size": 1.0}, {"color": "rgb(153,255,0)", "label": "597", "y": 1597.1, "x": 1106.9, "id": "597", "size": 1.0}, {"color": "rgb(153,255,0)", "label": "598", "y": 1001.3, "x": 438.97, "id": "598", "size": 1.0}, {"color": "rgb(153,255,0)", "label": "599", "y": 950.29, "x": 1079.3, "id": "599", "size": 1.0}, {"color": "rgb(153,255,0)", "label": "600", "y": 1602.5, "x": 1563.8, "id": "600", "size": 1.0}, {"color": "rgb(153,255,0)", "label": "601", "y": 1067.6, "x": 609.93, "id": "601", "size": 1.0}, {"color": "rgb(153,255,0)", "label": "602", "y": 790.39, "x": 1266.0, "id": "602", "size": 1.0}, {"color": "rgb(153,255,0)", "label": "603", "y": 1018.3, "x": 2175.0, "id": "603", "size": 1.0}, {"color": "rgb(153,255,0)", "label": "604", "y": 1044.2, "x": 802.84, "id": "604", "size": 1.0}, {"color": "rgb(153,255,0)", "label": "605", "y": 1478.9, "x": 274.76, "id": "605", "size": 1.0}, {"color": "rgb(153,255,0)", "label": "606", "y": 791.72, "x": 720.05, "id": "606", "size": 1.0}, {"color": "rgb(153,255,0)", "label": "607", "y": 1487.8, "x": 926.29, "id": "607", "size": 1.0}, {"color": "rgb(153,255,0)", "label": "608", "y": 1704.9, "x": 2675.0, "id": "608", "size": 1.0}, {"color": "rgb(153,255,0)", "label": "609", "y": 901.77, "x": 959.59, "id": "609", "size": 1.0}, {"color": "rgb(153,255,0)", "label": "610", "y": 2086.1, "x": 1127.4, "id": "610", "size": 1.0}, {"color": "rgb(153,255,0)", "label": "611", "y": 1273.1, "x": 628.71, "id": "611", "size": 1.0}, {"color": "rgb(153,255,0)", "label": "612", "y": 1207.0, "x": 1446.1, "id": "612", "size": 1.0}, {"color": "rgb(153,255,0)", "label": "613", "y": 1298.2, "x": 1679.0, "id": "613", "size": 1.0}, {"color": "rgb(153,255,0)", "label": "614", "y": 1545.1, "x": 1254.1, "id": "614", "size": 1.0}, {"color": "rgb(153,255,0)", "label": "615", "y": 873.02, "x": 1084.4, "id": "615", "size": 1.0}, {"color": "rgb(153,255,0)", "label": "616", "y": 915.76, "x": 589.1, "id": "616", "size": 1.0}, {"color": "rgb(153,255,0)", "label": "617", "y": 912.76, "x": 1246.9, "id": "617", "size": 1.0}, {"color": "rgb(153,255,0)", "label": "618", "y": 1274.4, "x": 1121.0, "id": "618", "size": 1.0}, {"color": "rgb(153,255,0)", "label": "619", "y": 1062.6, "x": 1109.4, "id": "619", "size": 1.0}, {"color": "rgb(153,255,0)", "label": "620", "y": 1304.0, "x": 1023.4, "id": "620", "size": 1.0}, {"color": "rgb(153,255,0)", "label": "621", "y": 995.61, "x": 1180.4, "id": "621", "size": 1.0}, {"color": "rgb(153,255,0)", "label": "622", "y": 1110.5, "x": 1231.5, "id": "622", "size": 1.0}, {"color": "rgb(153,255,0)", "label": "623", "y": 1587.1, "x": 587.71, "id": "623", "size": 1.0}, {"color": "rgb(153,255,0)", "label": "624", "y": 1436.4, "x": 621.61, "id": "624", "size": 1.0}, {"color": "rgb(153,255,0)", "label": "625", "y": 992.47, "x": 2150.4, "id": "625", "size": 1.0}, {"color": "rgb(153,255,0)", "label": "626", "y": 1746.4, "x": 942.88, "id": "626", "size": 1.0}, {"color": "rgb(153,255,0)", "label": "627", "y": 1127.9, "x": 902.39, "id": "627", "size": 1.0}, {"color": "rgb(153,255,0)", "label": "628", "y": 1396.7, "x": 1301.3, "id": "628", "size": 1.0}, {"color": "rgb(153,255,0)", "label": "629", "y": 1199.7, "x": 586.23, "id": "629", "size": 1.0}, {"color": "rgb(153,255,0)", "label": "630", "y": 1460.0, "x": 917.55, "id": "630", "size": 1.0}, {"color": "rgb(153,255,0)", "label": "631", "y": 1774.9, "x": 964.88, "id": "631", "size": 1.0}, {"color": "rgb(153,255,0)", "label": "632", "y": 799.07, "x": 438.61, "id": "632", "size": 1.0}, {"color": "rgb(153,255,0)", "label": "633", "y": 1730.8, "x": 644.0, "id": "633", "size": 1.0}, {"color": "rgb(153,255,0)", "label": "634", "y": 1560.2, "x": 711.98, "id": "634", "size": 1.0}, {"color": "rgb(153,255,0)", "label": "635", "y": 907.91, "x": 2020.4, "id": "635", "size": 1.0}, {"color": "rgb(153,255,0)", "label": "636", "y": 838.3, "x": 865.17, "id": "636", "size": 1.0}, {"color": "rgb(153,255,0)", "label": "637", "y": 1280.0, "x": 423.4, "id": "637", "size": 1.0}, {"color": "rgb(153,255,0)", "label": "638", "y": 1486.8, "x": 1512.3, "id": "638", "size": 1.0}, {"color": "rgb(153,255,0)", "label": "639", "y": 770.78, "x": 1991.4, "id": "639", "size": 1.0}, {"color": "rgb(153,255,0)", "label": "640", "y": 1157.8, "x": 672.32, "id": "640", "size": 1.0}, {"color": "rgb(153,255,0)", "label": "641", "y": 930.78, "x": 462.97, "id": "641", "size": 1.0}, {"color": "rgb(153,255,0)", "label": "642", "y": 1267.8, "x": 1571.0, "id": "642", "size": 1.0}, {"color": "rgb(153,255,0)", "label": "643", "y": 1454.0, "x": 954.73, "id": "643", "size": 1.0}, {"color": "rgb(153,255,0)", "label": "644", "y": 1088.7, "x": 1620.8, "id": "644", "size": 1.0}, {"color": "rgb(153,255,0)", "label": "645", "y": 1822.7, "x": 1240.2, "id": "645", "size": 1.0}, {"color": "rgb(153,255,0)", "label": "646", "y": 1567.3, "x": 1203.7, "id": "646", "size": 1.0}, {"color": "rgb(153,255,0)", "label": "647", "y": 617.75, "x": 2273.2, "id": "647", "size": 1.0}, {"color": "rgb(153,255,0)", "label": "648", "y": 1637.0, "x": 840.84, "id": "648", "size": 1.0}, {"color": "rgb(153,255,0)", "label": "649", "y": 632.49, "x": 681.94, "id": "649", "size": 1.0}, {"color": "rgb(153,255,0)", "label": "650", "y": 1275.6, "x": 1917.6, "id": "650", "size": 1.0}, {"color": "rgb(153,255,0)", "label": "651", "y": 1390.6, "x": 274.85, "id": "651", "size": 1.0}, {"color": "rgb(153,255,0)", "label": "652", "y": 1372.1, "x": 574.35, "id": "652", "size": 1.0}, {"color": "rgb(153,255,0)", "label": "653", "y": 2014.3, "x": 1366.2, "id": "653", "size": 1.0}, {"color": "rgb(153,255,0)", "label": "654", "y": 822.5, "x": 682.88, "id": "654", "size": 1.0}, {"color": "rgb(153,255,0)", "label": "655", "y": 1807.3, "x": 1473.3, "id": "655", "size": 1.0}, {"color": "rgb(153,255,0)", "label": "656", "y": 1736.3, "x": 1115.3, "id": "656", "size": 1.0}, {"color": "rgb(153,255,0)", "label": "657", "y": 1583.4, "x": 511.6, "id": "657", "size": 1.0}, {"color": "rgb(153,255,0)", "label": "658", "y": 902.75, "x": 1712.9, "id": "658", "size": 1.0}, {"color": "rgb(153,255,0)", "label": "659", "y": 1736.7, "x": 763.67, "id": "659", "size": 1.0}, {"color": "rgb(153,255,0)", "label": "660", "y": 1307.9, "x": 307.64, "id": "660", "size": 1.0}, {"color": "rgb(153,255,0)", "label": "661", "y": 1703.6, "x": 963.53, "id": "661", "size": 1.0}, {"color": "rgb(153,255,0)", "label": "662", "y": 823.0, "x": 622.6, "id": "662", "size": 1.0}, {"color": "rgb(153,255,0)", "label": "664", "y": 699.09, "x": 1946.5, "id": "664", "size": 1.0}, {"color": "rgb(153,255,0)", "label": "665", "y": 1392.2, "x": 448.08, "id": "665", "size": 1.0}, {"color": "rgb(153,255,0)", "label": "666", "y": 1344.0, "x": 109.45, "id": "666", "size": 1.0}, {"color": "rgb(153,255,0)", "label": "667", "y": 1254.0, "x": 895.68, "id": "667", "size": 1.0}, {"color": "rgb(153,255,0)", "label": "668", "y": 1666.5, "x": 749.29, "id": "668", "size": 1.0}, {"color": "rgb(153,255,0)", "label": "669", "y": 1492.2, "x": 1352.4, "id": "669", "size": 1.0}, {"color": "rgb(153,255,0)", "label": "670", "y": 806.72, "x": 1993.7, "id": "670", "size": 1.0}, {"color": "rgb(153,255,0)", "label": "671", "y": 1241.9, "x": 1134.5, "id": "671", "size": 1.0}, {"color": "rgb(153,255,0)", "label": "672", "y": 1715.3, "x": 2188.6, "id": "672", "size": 1.0}, {"color": "rgb(153,255,0)", "label": "673", "y": 1841.2, "x": 1224.4, "id": "673", "size": 1.0}, {"color": "rgb(153,255,0)", "label": "674", "y": 797.94, "x": 585.26, "id": "674", "size": 1.0}, {"color": "rgb(153,255,0)", "label": "675", "y": 1448.4, "x": 294.25, "id": "675", "size": 1.0}, {"color": "rgb(153,255,0)", "label": "676", "y": 856.74, "x": 296.61, "id": "676", "size": 1.0}, {"color": "rgb(153,255,0)", "label": "677", "y": 720.24, "x": 2190.3, "id": "677", "size": 1.0}, {"color": "rgb(153,255,0)", "label": "678", "y": 1528.8, "x": 969.8, "id": "678", "size": 1.0}, {"color": "rgb(153,255,0)", "label": "679", "y": 301.36, "x": 2253.7, "id": "679", "size": 1.0}, {"color": "rgb(153,255,0)", "label": "680", "y": 1428.6, "x": 1156.0, "id": "680", "size": 1.0}, {"color": "rgb(153,255,0)", "label": "681", "y": 1042.5, "x": 224.83, "id": "681", "size": 1.0}, {"color": "rgb(153,255,0)", "label": "682", "y": 1600.0, "x": 1378.5, "id": "682", "size": 1.0}, {"color": "rgb(153,255,0)", "label": "683", "y": 1566.8, "x": 1150.8, "id": "683", "size": 1.0}, {"color": "rgb(153,255,0)", "label": "684", "y": 1421.0, "x": 1407.4, "id": "684", "size": 1.0}, {"color": "rgb(153,255,0)", "label": "685", "y": 1295.4, "x": 1381.7, "id": "685", "size": 1.0}, {"color": "rgb(153,255,0)", "label": "686", "y": 677.19, "x": 1992.2, "id": "686", "size": 1.0}, {"color": "rgb(153,255,0)", "label": "687", "y": 1519.8, "x": 701.96, "id": "687", "size": 1.0}, {"color": "rgb(153,255,0)", "label": "688", "y": 1748.8, "x": 1034.7, "id": "688", "size": 1.0}, {"color": "rgb(153,255,0)", "label": "689", "y": 798.72, "x": 1934.3, "id": "689", "size": 1.0}, {"color": "rgb(153,255,0)", "label": "690", "y": 1016.1, "x": 1409.9, "id": "690", "size": 1.0}, {"color": "rgb(153,255,0)", "label": "691", "y": 1166.9, "x": 391.62, "id": "691", "size": 1.0}, {"color": "rgb(153,255,0)", "label": "692", "y": 662.26, "x": 1627.7, "id": "692", "size": 1.0}, {"color": "rgb(153,255,0)", "label": "693", "y": 1001.5, "x": 794.43, "id": "693", "size": 1.0}, {"color": "rgb(153,255,0)", "label": "694", "y": 1470.5, "x": 983.65, "id": "694", "size": 1.0}, {"color": "rgb(153,255,0)", "label": "695", "y": 499.38, "x": 1489.5, "id": "695", "size": 1.0}, {"color": "rgb(153,255,0)", "label": "696", "y": 1613.8, "x": 534.09, "id": "696", "size": 1.0}, {"color": "rgb(153,255,0)", "label": "697", "y": 1078.9, "x": 630.53, "id": "697", "size": 1.0}, {"color": "rgb(153,255,0)", "label": "698", "y": 1447.5, "x": 1329.4, "id": "698", "size": 1.0}, {"color": "rgb(153,255,0)", "label": "699", "y": 946.69, "x": 610.74, "id": "699", "size": 1.0}, {"color": "rgb(153,255,0)", "label": "700", "y": 919.19, "x": 1025.1, "id": "700", "size": 1.0}, {"color": "rgb(153,255,0)", "label": "701", "y": 1652.5, "x": 633.98, "id": "701", "size": 1.0}, {"color": "rgb(153,255,0)", "label": "702", "y": 835.88, "x": 2011.2, "id": "702", "size": 1.0}, {"color": "rgb(153,255,0)", "label": "703", "y": 1024.6, "x": 517.12, "id": "703", "size": 1.0}, {"color": "rgb(153,255,0)", "label": "704", "y": 1032.9, "x": 399.03, "id": "704", "size": 1.0}, {"color": "rgb(153,255,0)", "label": "705", "y": 1240.8, "x": 1208.0, "id": "705", "size": 1.0}, {"color": "rgb(153,255,0)", "label": "706", "y": 772.35, "x": 581.93, "id": "706", "size": 1.0}, {"color": "rgb(153,255,0)", "label": "707", "y": 1352.4, "x": 2570.7, "id": "707", "size": 1.0}, {"color": "rgb(153,255,0)", "label": "708", "y": 1299.0, "x": 1921.2, "id": "708", "size": 1.0}, {"color": "rgb(153,255,0)", "label": "709", "y": 1675.5, "x": 977.71, "id": "709", "size": 1.0}, {"color": "rgb(153,255,0)", "label": "710", "y": 1657.7, "x": 1243.5, "id": "710", "size": 1.0}, {"color": "rgb(153,255,0)", "label": "711", "y": 1697.2, "x": 1049.6, "id": "711", "size": 1.0}, {"color": "rgb(153,255,0)", "label": "712", "y": 1554.4, "x": 1029.2, "id": "712", "size": 1.0}, {"color": "rgb(153,255,0)", "label": "713", "y": 1336.3, "x": 894.07, "id": "713", "size": 1.0}, {"color": "rgb(153,255,0)", "label": "714", "y": 974.13, "x": 982.13, "id": "714", "size": 1.0}, {"color": "rgb(153,255,0)", "label": "715", "y": 755.64, "x": 270.64, "id": "715", "size": 1.0}, {"color": "rgb(153,255,0)", "label": "716", "y": 1871.5, "x": 1183.9, "id": "716", "size": 1.0}, {"color": "rgb(153,255,0)", "label": "717", "y": 1541.0, "x": 1238.3, "id": "717", "size": 1.0}, {"color": "rgb(153,255,0)", "label": "718", "y": 1706.0, "x": 1190.9, "id": "718", "size": 1.0}, {"color": "rgb(153,255,0)", "label": "719", "y": 1568.1, "x": 812.15, "id": "719", "size": 1.0}, {"color": "rgb(153,255,0)", "label": "720", "y": 1075.5, "x": 1073.4, "id": "720", "size": 1.0}, {"color": "rgb(153,255,0)", "label": "721", "y": 1919.6, "x": 1689.3, "id": "721", "size": 1.0}, {"color": "rgb(153,255,0)", "label": "722", "y": 1152.3, "x": 858.95, "id": "722", "size": 1.0}, {"color": "rgb(153,255,0)", "label": "723", "y": 1684.8, "x": 897.54, "id": "723", "size": 1.0}, {"color": "rgb(153,255,0)", "label": "724", "y": 1234.8, "x": 830.65, "id": "724", "size": 1.0}, {"color": "rgb(153,255,0)", "label": "725", "y": 1254.8, "x": 1463.9, "id": "725", "size": 1.0}, {"color": "rgb(153,255,0)", "label": "726", "y": 1616.3, "x": 981.01, "id": "726", "size": 1.0}, {"color": "rgb(153,255,0)", "label": "727", "y": 1519.3, "x": 1516.7, "id": "727", "size": 1.0}, {"color": "rgb(153,255,0)", "label": "728", "y": 1426.1, "x": 1352.0, "id": "728", "size": 1.0}]}